construction_utils/__init__.py
construction_utils/__main__.py
construction_utils/_version.py
construction_utils/freecad_exporter.py
construction_utils/main.py
construction_utils/project_creator.py
construction_utils/py.typed
construction_utils/readme_generator.py
construction_utils/resources/img/no_image_available.png
construction_utils/resources/img/origins.csv
construction_utils/resources/scripts/freecad_export_image_script.py
construction_utils/resources/templates/origins.csv
construction_utils/resources/templates/template_construction.json.jinja
construction_utils/resources/templates/template_construction_readme.md.jinja
construction_utils/resources/templates/template_workspace_readme.md.jinja
construction_utils-0.2.1.dist-info/LICENSE
construction_utils-0.2.1.dist-info/METADATA
construction_utils-0.2.1.dist-info/WHEEL
construction_utils-0.2.1.dist-info/entry_points.txt
construction_utils-0.2.1.dist-info/top_level.txt
construction_utils-0.2.1.dist-info/RECORD
