Metadata-Version: 2.1
Name: construction_utils
Version: 0.2.1
Summary: Utilities for FreeCAD construction workspaces.
Home-page: https://github.com/twyleg/construction_utils
Author: Torsten Wylegala
Author-email: mail@twyleg.de
License: GPL 3.0
Keywords: FreeCAD Export Constructions Generator Utilities
License-File: LICENSE
Requires-Dist: simple-python-app ~=0.4.0
Requires-Dist: jinja2 ~=3.1.4
